setup.py
Tornado_Babel.egg-info/PKG-INFO
Tornado_Babel.egg-info/SOURCES.txt
Tornado_Babel.egg-info/dependency_links.txt
Tornado_Babel.egg-info/entry_points.txt
Tornado_Babel.egg-info/requires.txt
Tornado_Babel.egg-info/top_level.txt
tests/__init__.py
tests/test_extract.py
tests/test_locale.py
tests/test_merge.py
tornadobabel/__init__.py
tornadobabel/extract.py
tornadobabel/locale.py
tornadobabel/mixin.py