Metadata-Version: 1.0
Name: Tornado-Babel
Version: 0.2
Summary: Babel localisation support for Torando
Home-page: https://github.com/openlabs/tornado-babel
Author: Openlabs Technologies & Consulting (P) Limited
Author-email: info@openlabs.co.in
License: BSD
Keywords: tornado locale babel localisation
Platform: UNKNOWN
